pagerd_snapf/__init__.py
pagerd_snapf/functions.py
pagerd_snapf-1.2.dist-info/METADATA
pagerd_snapf-1.2.dist-info/WHEEL
pagerd_snapf-1.2.dist-info/top_level.txt
pagerd_snapf-1.2.dist-info/RECORD
