Metadata-Version: 2.1
Name: pagerd-snapf
Version: 1.2
Summary: Package for interacting with PagerDuty service
Home-page: UNKNOWN
Author: Mauricio Ayales
Author-email: mayales@snapfinance.com
License: UNKNOWN
Platform: UNKNOWN
Requires-Dist: requests
